<?xml version="1.0" encoding="UTF-8"?>
<?xml-stylesheet href="CoreNLP-to-HTML.xsl" type="text/xsl"?>
<root>
  <document>
    <sentences>
      <sentence id="1">
        <tokens>
          <token id="1">
            <word>&lt;DOC&gt;</word>
            <lemma>&lt;doc&gt;</lemma>
            <CharacterOffsetBegin>0</CharacterOffsetBegin>
            <CharacterOffsetEnd>5</CharacterOffsetEnd>
            <POS>NN</POS>
            <TrueCase>O</TrueCase>
            <TrueCaseText>&lt;DOC&gt;</TrueCaseText>
          </token>
          <token id="2">
            <word>&lt;DOCID&gt;</word>
            <lemma>&lt;docid&gt;</lemma>
            <CharacterOffsetBegin>6</CharacterOffsetBegin>
            <CharacterOffsetEnd>13</CharacterOffsetEnd>
            <POS>NN</POS>
            <TrueCase>O</TrueCase>
            <TrueCaseText>&lt;DOCID&gt;</TrueCaseText>
          </token>
          <token id="3">
            <word>CNN_ENG_20030604_092828</word>
            <lemma>cnn_eng_20030604_092828</lemma>
            <CharacterOffsetBegin>14</CharacterOffsetBegin>
            <CharacterOffsetEnd>37</CharacterOffsetEnd>
            <POS>NN</POS>
            <TrueCase>O</TrueCase>
            <TrueCaseText>CNN_ENG_20030604_092828</TrueCaseText>
          </token>
          <token id="4">
            <word>.7</word>
            <lemma>.7</lemma>
            <CharacterOffsetBegin>37</CharacterOffsetBegin>
            <CharacterOffsetEnd>39</CharacterOffsetEnd>
            <POS>CD</POS>
            <TrueCase>O</TrueCase>
            <TrueCaseText>.7</TrueCaseText>
          </token>
          <token id="5">
            <word>&lt;/DOCID&gt;</word>
            <lemma>&lt;/docid&gt;</lemma>
            <CharacterOffsetBegin>40</CharacterOffsetBegin>
            <CharacterOffsetEnd>48</CharacterOffsetEnd>
            <POS>NN</POS>
            <TrueCase>O</TrueCase>
            <TrueCaseText>&lt;/DOCID&gt;</TrueCaseText>
          </token>
          <token id="6">
            <word>&lt;DOCTYPE SOURCE="broadcast news"&gt;</word>
            <lemma>&lt;doctype source="broadcast news"&gt;</lemma>
            <CharacterOffsetBegin>49</CharacterOffsetBegin>
            <CharacterOffsetEnd>82</CharacterOffsetEnd>
            <POS>NN</POS>
            <TrueCase>O</TrueCase>
            <TrueCaseText>&lt;DOCTYPE SOURCE="broadcast news"&gt;</TrueCaseText>
          </token>
          <token id="7">
            <word>NEWS</word>
            <lemma>news</lemma>
            <CharacterOffsetBegin>83</CharacterOffsetBegin>
            <CharacterOffsetEnd>87</CharacterOffsetEnd>
            <POS>NN</POS>
            <TrueCase>O</TrueCase>
            <TrueCaseText>NEWS</TrueCaseText>
          </token>
          <token id="8">
            <word>STORY</word>
            <lemma>story</lemma>
            <CharacterOffsetBegin>88</CharacterOffsetBegin>
            <CharacterOffsetEnd>93</CharacterOffsetEnd>
            <POS>NN</POS>
            <TrueCase>O</TrueCase>
            <TrueCaseText>STORY</TrueCaseText>
          </token>
          <token id="9">
            <word>&lt;/DOCTYPE&gt;</word>
            <lemma>&lt;/doctype&gt;</lemma>
            <CharacterOffsetBegin>94</CharacterOffsetBegin>
            <CharacterOffsetEnd>104</CharacterOffsetEnd>
            <POS>NN</POS>
            <TrueCase>O</TrueCase>
            <TrueCaseText>&lt;/DOCTYPE&gt;</TrueCaseText>
          </token>
          <token id="10">
            <word>&lt;DATETIME&gt;</word>
            <lemma>&lt;datetime&gt;</lemma>
            <CharacterOffsetBegin>105</CharacterOffsetBegin>
            <CharacterOffsetEnd>115</CharacterOffsetEnd>
            <POS>NN</POS>
            <TrueCase>O</TrueCase>
            <TrueCaseText>&lt;DATETIME&gt;</TrueCaseText>
          </token>
          <token id="11">
            <word>2003-06-04</word>
            <lemma>2003-06-04</lemma>
            <CharacterOffsetBegin>116</CharacterOffsetBegin>
            <CharacterOffsetEnd>126</CharacterOffsetEnd>
            <POS>CD</POS>
            <TrueCase>O</TrueCase>
            <TrueCaseText>2003-06-04</TrueCaseText>
          </token>
          <token id="12">
            <word>09:42:13</word>
            <lemma>09:42:13</lemma>
            <CharacterOffsetBegin>127</CharacterOffsetBegin>
            <CharacterOffsetEnd>135</CharacterOffsetEnd>
            <POS>CD</POS>
            <TrueCase>O</TrueCase>
            <TrueCaseText>09:42:13</TrueCaseText>
          </token>
          <token id="13">
            <word>&lt;/DATETIME&gt;</word>
            <lemma>&lt;/datetime&gt;</lemma>
            <CharacterOffsetBegin>136</CharacterOffsetBegin>
            <CharacterOffsetEnd>147</CharacterOffsetEnd>
            <POS>NN</POS>
            <TrueCase>O</TrueCase>
            <TrueCaseText>&lt;/DATETIME&gt;</TrueCaseText>
          </token>
          <token id="14">
            <word>&lt;BODY&gt;</word>
            <lemma>&lt;body&gt;</lemma>
            <CharacterOffsetBegin>148</CharacterOffsetBegin>
            <CharacterOffsetEnd>154</CharacterOffsetEnd>
            <POS>NN</POS>
            <TrueCase>O</TrueCase>
            <TrueCaseText>&lt;BODY&gt;</TrueCaseText>
          </token>
          <token id="15">
            <word>&lt;TEXT&gt;</word>
            <lemma>&lt;text&gt;</lemma>
            <CharacterOffsetBegin>155</CharacterOffsetBegin>
            <CharacterOffsetEnd>161</CharacterOffsetEnd>
            <POS>NN</POS>
            <TrueCase>O</TrueCase>
            <TrueCaseText>&lt;TEXT&gt;</TrueCaseText>
          </token>
          <token id="16">
            <word>&lt;TURN&gt;</word>
            <lemma>&lt;turn&gt;</lemma>
            <CharacterOffsetBegin>162</CharacterOffsetBegin>
            <CharacterOffsetEnd>168</CharacterOffsetEnd>
            <POS>NN</POS>
            <TrueCase>O</TrueCase>
            <TrueCaseText>&lt;TURN&gt;</TrueCaseText>
          </token>
          <token id="17">
            <word>moving</word>
            <lemma>move</lemma>
            <CharacterOffsetBegin>169</CharacterOffsetBegin>
            <CharacterOffsetEnd>175</CharacterOffsetEnd>
            <POS>VBG</POS>
            <TrueCase>LOWER</TrueCase>
            <TrueCaseText>moving</TrueCaseText>
          </token>
          <token id="18">
            <word>onto</word>
            <lemma>onto</lemma>
            <CharacterOffsetBegin>176</CharacterOffsetBegin>
            <CharacterOffsetEnd>180</CharacterOffsetEnd>
            <POS>IN</POS>
            <TrueCase>LOWER</TrueCase>
            <TrueCaseText>onto</TrueCaseText>
          </token>
          <token id="19">
            <word>the</word>
            <lemma>the</lemma>
            <CharacterOffsetBegin>181</CharacterOffsetBegin>
            <CharacterOffsetEnd>184</CharacterOffsetEnd>
            <POS>DT</POS>
            <TrueCase>LOWER</TrueCase>
            <TrueCaseText>the</TrueCaseText>
          </token>
          <token id="20">
            <word>laci</word>
            <lemma>lacus</lemma>
            <CharacterOffsetBegin>185</CharacterOffsetBegin>
            <CharacterOffsetEnd>189</CharacterOffsetEnd>
            <POS>NN</POS>
            <TrueCase>UPPER</TrueCase>
            <TrueCaseText>LACI</TrueCaseText>
          </token>
          <token id="21">
            <word>peterson</word>
            <lemma>peterson</lemma>
            <CharacterOffsetBegin>190</CharacterOffsetBegin>
            <CharacterOffsetEnd>198</CharacterOffsetEnd>
            <POS>NN</POS>
            <TrueCase>INIT_UPPER</TrueCase>
            <TrueCaseText>Peterson</TrueCaseText>
          </token>
          <token id="22">
            <word>case</word>
            <lemma>case</lemma>
            <CharacterOffsetBegin>199</CharacterOffsetBegin>
            <CharacterOffsetEnd>203</CharacterOffsetEnd>
            <POS>NN</POS>
            <TrueCase>LOWER</TrueCase>
            <TrueCaseText>case</TrueCaseText>
          </token>
          <token id="23">
            <word>bill</word>
            <lemma>bill</lemma>
            <CharacterOffsetBegin>204</CharacterOffsetBegin>
            <CharacterOffsetEnd>208</CharacterOffsetEnd>
            <POS>NN</POS>
            <TrueCase>LOWER</TrueCase>
            <TrueCaseText>bill</TrueCaseText>
          </token>
          <token id="24">
            <word>,</word>
            <lemma>,</lemma>
            <CharacterOffsetBegin>208</CharacterOffsetBegin>
            <CharacterOffsetEnd>209</CharacterOffsetEnd>
            <POS>,</POS>
            <TrueCase>O</TrueCase>
            <TrueCaseText>,</TrueCaseText>
          </token>
          <token id="25">
            <word>an</word>
            <lemma>a</lemma>
            <CharacterOffsetBegin>210</CharacterOffsetBegin>
            <CharacterOffsetEnd>212</CharacterOffsetEnd>
            <POS>DT</POS>
            <TrueCase>LOWER</TrueCase>
            <TrueCaseText>an</TrueCaseText>
          </token>
          <token id="26">
            <word>unusual</word>
            <lemma>unusual</lemma>
            <CharacterOffsetBegin>213</CharacterOffsetBegin>
            <CharacterOffsetEnd>220</CharacterOffsetEnd>
            <POS>JJ</POS>
            <TrueCase>LOWER</TrueCase>
            <TrueCaseText>unusual</TrueCaseText>
          </token>
          <token id="27">
            <word>request</word>
            <lemma>request</lemma>
            <CharacterOffsetBegin>221</CharacterOffsetBegin>
            <CharacterOffsetEnd>228</CharacterOffsetEnd>
            <POS>NN</POS>
            <TrueCase>LOWER</TrueCase>
            <TrueCaseText>request</TrueCaseText>
          </token>
          <token id="28">
            <word>from</word>
            <lemma>from</lemma>
            <CharacterOffsetBegin>229</CharacterOffsetBegin>
            <CharacterOffsetEnd>233</CharacterOffsetEnd>
            <POS>IN</POS>
            <TrueCase>LOWER</TrueCase>
            <TrueCaseText>from</TrueCaseText>
          </token>
          <token id="29">
            <word>scott</word>
            <lemma>scott</lemma>
            <CharacterOffsetBegin>234</CharacterOffsetBegin>
            <CharacterOffsetEnd>239</CharacterOffsetEnd>
            <POS>NN</POS>
            <TrueCase>INIT_UPPER</TrueCase>
            <TrueCaseText>Scott</TrueCaseText>
          </token>
          <token id="30">
            <word>peterson</word>
            <lemma>peterson</lemma>
            <CharacterOffsetBegin>240</CharacterOffsetBegin>
            <CharacterOffsetEnd>248</CharacterOffsetEnd>
            <POS>NN</POS>
            <TrueCase>INIT_UPPER</TrueCase>
            <TrueCaseText>Peterson</TrueCaseText>
          </token>
          <token id="31">
            <word>'s</word>
            <lemma>'s</lemma>
            <CharacterOffsetBegin>248</CharacterOffsetBegin>
            <CharacterOffsetEnd>250</CharacterOffsetEnd>
            <POS>POS</POS>
            <TrueCase>LOWER</TrueCase>
            <TrueCaseText>'s</TrueCaseText>
          </token>
          <token id="32">
            <word>attorney</word>
            <lemma>attorney</lemma>
            <CharacterOffsetBegin>251</CharacterOffsetBegin>
            <CharacterOffsetEnd>259</CharacterOffsetEnd>
            <POS>NN</POS>
            <TrueCase>LOWER</TrueCase>
            <TrueCaseText>attorney</TrueCaseText>
          </token>
          <token id="33">
            <word>.</word>
            <lemma>.</lemma>
            <CharacterOffsetBegin>259</CharacterOffsetBegin>
            <CharacterOffsetEnd>260</CharacterOffsetEnd>
            <POS>.</POS>
            <TrueCase>O</TrueCase>
            <TrueCaseText>.</TrueCaseText>
          </token>
        </tokens>
      </sentence>
      <sentence id="2">
        <tokens>
          <token id="1">
            <word>a</word>
            <lemma>a</lemma>
            <CharacterOffsetBegin>261</CharacterOffsetBegin>
            <CharacterOffsetEnd>262</CharacterOffsetEnd>
            <POS>DT</POS>
            <TrueCase>UPPER</TrueCase>
            <TrueCaseText>A</TrueCaseText>
          </token>
          <token id="2">
            <word>pair</word>
            <lemma>pair</lemma>
            <CharacterOffsetBegin>263</CharacterOffsetBegin>
            <CharacterOffsetEnd>267</CharacterOffsetEnd>
            <POS>NN</POS>
            <TrueCase>LOWER</TrueCase>
            <TrueCaseText>pair</TrueCaseText>
          </token>
          <token id="3">
            <word>of</word>
            <lemma>of</lemma>
            <CharacterOffsetBegin>268</CharacterOffsetBegin>
            <CharacterOffsetEnd>270</CharacterOffsetEnd>
            <POS>IN</POS>
            <TrueCase>LOWER</TrueCase>
            <TrueCaseText>of</TrueCaseText>
          </token>
          <token id="4">
            <word>laci</word>
            <lemma>lacus</lemma>
            <CharacterOffsetBegin>271</CharacterOffsetBegin>
            <CharacterOffsetEnd>275</CharacterOffsetEnd>
            <POS>NN</POS>
            <TrueCase>UPPER</TrueCase>
            <TrueCaseText>LACI</TrueCaseText>
          </token>
          <token id="5">
            <word>peterson</word>
            <lemma>peterson</lemma>
            <CharacterOffsetBegin>276</CharacterOffsetBegin>
            <CharacterOffsetEnd>284</CharacterOffsetEnd>
            <POS>NN</POS>
            <TrueCase>INIT_UPPER</TrueCase>
            <TrueCaseText>Peterson</TrueCaseText>
          </token>
          <token id="6">
            <word>'s</word>
            <lemma>'s</lemma>
            <CharacterOffsetBegin>284</CharacterOffsetBegin>
            <CharacterOffsetEnd>286</CharacterOffsetEnd>
            <POS>POS</POS>
            <TrueCase>LOWER</TrueCase>
            <TrueCaseText>'s</TrueCaseText>
          </token>
          <token id="7">
            <word>missing</word>
            <lemma>missing</lemma>
            <CharacterOffsetBegin>287</CharacterOffsetBegin>
            <CharacterOffsetEnd>294</CharacterOffsetEnd>
            <POS>JJ</POS>
            <TrueCase>LOWER</TrueCase>
            <TrueCaseText>missing</TrueCaseText>
          </token>
          <token id="8">
            <word>shoes</word>
            <lemma>shoe</lemma>
            <CharacterOffsetBegin>295</CharacterOffsetBegin>
            <CharacterOffsetEnd>300</CharacterOffsetEnd>
            <POS>NNS</POS>
            <TrueCase>LOWER</TrueCase>
            <TrueCaseText>shoes</TrueCaseText>
          </token>
          <token id="9">
            <word>could</word>
            <lemma>could</lemma>
            <CharacterOffsetBegin>301</CharacterOffsetBegin>
            <CharacterOffsetEnd>306</CharacterOffsetEnd>
            <POS>MD</POS>
            <TrueCase>LOWER</TrueCase>
            <TrueCaseText>could</TrueCaseText>
          </token>
          <token id="10">
            <word>be</word>
            <lemma>be</lemma>
            <CharacterOffsetBegin>307</CharacterOffsetBegin>
            <CharacterOffsetEnd>309</CharacterOffsetEnd>
            <POS>VB</POS>
            <TrueCase>LOWER</TrueCase>
            <TrueCaseText>be</TrueCaseText>
          </token>
          <token id="11">
            <word>very</word>
            <lemma>very</lemma>
            <CharacterOffsetBegin>310</CharacterOffsetBegin>
            <CharacterOffsetEnd>314</CharacterOffsetEnd>
            <POS>RB</POS>
            <TrueCase>LOWER</TrueCase>
            <TrueCaseText>very</TrueCaseText>
          </token>
          <token id="12">
            <word>important</word>
            <lemma>important</lemma>
            <CharacterOffsetBegin>315</CharacterOffsetBegin>
            <CharacterOffsetEnd>324</CharacterOffsetEnd>
            <POS>JJ</POS>
            <TrueCase>LOWER</TrueCase>
            <TrueCaseText>important</TrueCaseText>
          </token>
          <token id="13">
            <word>evidence</word>
            <lemma>evidence</lemma>
            <CharacterOffsetBegin>325</CharacterOffsetBegin>
            <CharacterOffsetEnd>333</CharacterOffsetEnd>
            <POS>NN</POS>
            <TrueCase>LOWER</TrueCase>
            <TrueCaseText>evidence</TrueCaseText>
          </token>
          <token id="14">
            <word>in</word>
            <lemma>in</lemma>
            <CharacterOffsetBegin>334</CharacterOffsetBegin>
            <CharacterOffsetEnd>336</CharacterOffsetEnd>
            <POS>IN</POS>
            <TrueCase>LOWER</TrueCase>
            <TrueCaseText>in</TrueCaseText>
          </token>
          <token id="15">
            <word>scott</word>
            <lemma>scott</lemma>
            <CharacterOffsetBegin>337</CharacterOffsetBegin>
            <CharacterOffsetEnd>342</CharacterOffsetEnd>
            <POS>NN</POS>
            <TrueCase>INIT_UPPER</TrueCase>
            <TrueCaseText>Scott</TrueCaseText>
          </token>
          <token id="16">
            <word>'s</word>
            <lemma>'s</lemma>
            <CharacterOffsetBegin>342</CharacterOffsetBegin>
            <CharacterOffsetEnd>344</CharacterOffsetEnd>
            <POS>POS</POS>
            <TrueCase>LOWER</TrueCase>
            <TrueCaseText>'s</TrueCaseText>
          </token>
          <token id="17">
            <word>murder</word>
            <lemma>murder</lemma>
            <CharacterOffsetBegin>345</CharacterOffsetBegin>
            <CharacterOffsetEnd>351</CharacterOffsetEnd>
            <POS>NN</POS>
            <TrueCase>LOWER</TrueCase>
            <TrueCaseText>murder</TrueCaseText>
          </token>
          <token id="18">
            <word>trial</word>
            <lemma>trial</lemma>
            <CharacterOffsetBegin>352</CharacterOffsetBegin>
            <CharacterOffsetEnd>357</CharacterOffsetEnd>
            <POS>NN</POS>
            <TrueCase>LOWER</TrueCase>
            <TrueCaseText>trial</TrueCaseText>
          </token>
          <token id="19">
            <word>.</word>
            <lemma>.</lemma>
            <CharacterOffsetBegin>357</CharacterOffsetBegin>
            <CharacterOffsetEnd>358</CharacterOffsetEnd>
            <POS>.</POS>
            <TrueCase>O</TrueCase>
            <TrueCaseText>.</TrueCaseText>
          </token>
        </tokens>
      </sentence>
      <sentence id="3">
        <tokens>
          <token id="1">
            <word>she</word>
            <lemma>she</lemma>
            <CharacterOffsetBegin>359</CharacterOffsetBegin>
            <CharacterOffsetEnd>362</CharacterOffsetEnd>
            <POS>PRP</POS>
            <TrueCase>INIT_UPPER</TrueCase>
            <TrueCaseText>She</TrueCaseText>
          </token>
          <token id="2">
            <word>asking</word>
            <lemma>ask</lemma>
            <CharacterOffsetBegin>363</CharacterOffsetBegin>
            <CharacterOffsetEnd>369</CharacterOffsetEnd>
            <POS>VBG</POS>
            <TrueCase>LOWER</TrueCase>
            <TrueCaseText>asking</TrueCaseText>
          </token>
          <token id="3">
            <word>anyone</word>
            <lemma>anyone</lemma>
            <CharacterOffsetBegin>370</CharacterOffsetBegin>
            <CharacterOffsetEnd>376</CharacterOffsetEnd>
            <POS>NN</POS>
            <TrueCase>LOWER</TrueCase>
            <TrueCaseText>anyone</TrueCaseText>
          </token>
          <token id="4">
            <word>who</word>
            <lemma>who</lemma>
            <CharacterOffsetBegin>377</CharacterOffsetBegin>
            <CharacterOffsetEnd>380</CharacterOffsetEnd>
            <POS>WP</POS>
            <TrueCase>LOWER</TrueCase>
            <TrueCaseText>who</TrueCaseText>
          </token>
          <token id="5">
            <word>finds</word>
            <lemma>find</lemma>
            <CharacterOffsetBegin>381</CharacterOffsetBegin>
            <CharacterOffsetEnd>386</CharacterOffsetEnd>
            <POS>VBZ</POS>
            <TrueCase>LOWER</TrueCase>
            <TrueCaseText>finds</TrueCaseText>
          </token>
          <token id="6">
            <word>the</word>
            <lemma>the</lemma>
            <CharacterOffsetBegin>387</CharacterOffsetBegin>
            <CharacterOffsetEnd>390</CharacterOffsetEnd>
            <POS>DT</POS>
            <TrueCase>LOWER</TrueCase>
            <TrueCaseText>the</TrueCaseText>
          </token>
          <token id="7">
            <word>pair</word>
            <lemma>pair</lemma>
            <CharacterOffsetBegin>391</CharacterOffsetBegin>
            <CharacterOffsetEnd>395</CharacterOffsetEnd>
            <POS>NN</POS>
            <TrueCase>LOWER</TrueCase>
            <TrueCaseText>pair</TrueCaseText>
          </token>
          <token id="8">
            <word>to</word>
            <lemma>to</lemma>
            <CharacterOffsetBegin>396</CharacterOffsetBegin>
            <CharacterOffsetEnd>398</CharacterOffsetEnd>
            <POS>TO</POS>
            <TrueCase>LOWER</TrueCase>
            <TrueCaseText>to</TrueCaseText>
          </token>
          <token id="9">
            <word>give</word>
            <lemma>give</lemma>
            <CharacterOffsetBegin>399</CharacterOffsetBegin>
            <CharacterOffsetEnd>403</CharacterOffsetEnd>
            <POS>VB</POS>
            <TrueCase>LOWER</TrueCase>
            <TrueCaseText>give</TrueCaseText>
          </token>
          <token id="10">
            <word>them</word>
            <lemma>they</lemma>
            <CharacterOffsetBegin>404</CharacterOffsetBegin>
            <CharacterOffsetEnd>408</CharacterOffsetEnd>
            <POS>PRP</POS>
            <TrueCase>LOWER</TrueCase>
            <TrueCaseText>them</TrueCaseText>
          </token>
          <token id="11">
            <word>back</word>
            <lemma>back</lemma>
            <CharacterOffsetBegin>409</CharacterOffsetBegin>
            <CharacterOffsetEnd>413</CharacterOffsetEnd>
            <POS>RB</POS>
            <TrueCase>LOWER</TrueCase>
            <TrueCaseText>back</TrueCaseText>
          </token>
          <token id="12">
            <word>.</word>
            <lemma>.</lemma>
            <CharacterOffsetBegin>413</CharacterOffsetBegin>
            <CharacterOffsetEnd>414</CharacterOffsetEnd>
            <POS>.</POS>
            <TrueCase>O</TrueCase>
            <TrueCaseText>.</TrueCaseText>
          </token>
        </tokens>
      </sentence>
      <sentence id="4">
        <tokens>
          <token id="1">
            <word>no</word>
            <lemma>no</lemma>
            <CharacterOffsetBegin>415</CharacterOffsetBegin>
            <CharacterOffsetEnd>417</CharacterOffsetEnd>
            <POS>DT</POS>
            <TrueCase>INIT_UPPER</TrueCase>
            <TrueCaseText>No</TrueCaseText>
          </token>
          <token id="2">
            <word>sign</word>
            <lemma>sign</lemma>
            <CharacterOffsetBegin>418</CharacterOffsetBegin>
            <CharacterOffsetEnd>422</CharacterOffsetEnd>
            <POS>NN</POS>
            <TrueCase>LOWER</TrueCase>
            <TrueCaseText>sign</TrueCaseText>
          </token>
          <token id="3">
            <word>of</word>
            <lemma>of</lemma>
            <CharacterOffsetBegin>423</CharacterOffsetBegin>
            <CharacterOffsetEnd>425</CharacterOffsetEnd>
            <POS>IN</POS>
            <TrueCase>LOWER</TrueCase>
            <TrueCaseText>of</TrueCaseText>
          </token>
          <token id="4">
            <word>geragos</word>
            <lemma>gerago</lemma>
            <CharacterOffsetBegin>426</CharacterOffsetBegin>
            <CharacterOffsetEnd>433</CharacterOffsetEnd>
            <POS>NNS</POS>
            <TrueCase>UPPER</TrueCase>
            <TrueCaseText>GERAGOS</TrueCaseText>
          </token>
          <token id="5">
            <word>or</word>
            <lemma>or</lemma>
            <CharacterOffsetBegin>434</CharacterOffsetBegin>
            <CharacterOffsetEnd>436</CharacterOffsetEnd>
            <POS>CC</POS>
            <TrueCase>LOWER</TrueCase>
            <TrueCaseText>or</TrueCaseText>
          </token>
          <token id="6">
            <word>peterson</word>
            <lemma>peterson</lemma>
            <CharacterOffsetBegin>437</CharacterOffsetBegin>
            <CharacterOffsetEnd>445</CharacterOffsetEnd>
            <POS>NN</POS>
            <TrueCase>INIT_UPPER</TrueCase>
            <TrueCaseText>Peterson</TrueCaseText>
          </token>
          <token id="7">
            <word>in</word>
            <lemma>in</lemma>
            <CharacterOffsetBegin>446</CharacterOffsetBegin>
            <CharacterOffsetEnd>448</CharacterOffsetEnd>
            <POS>IN</POS>
            <TrueCase>LOWER</TrueCase>
            <TrueCaseText>in</TrueCaseText>
          </token>
          <token id="8">
            <word>court</word>
            <lemma>court</lemma>
            <CharacterOffsetBegin>449</CharacterOffsetBegin>
            <CharacterOffsetEnd>454</CharacterOffsetEnd>
            <POS>NN</POS>
            <TrueCase>LOWER</TrueCase>
            <TrueCaseText>court</TrueCaseText>
          </token>
          <token id="9">
            <word>yesterday</word>
            <lemma>yesterday</lemma>
            <CharacterOffsetBegin>455</CharacterOffsetBegin>
            <CharacterOffsetEnd>464</CharacterOffsetEnd>
            <POS>NN</POS>
            <TrueCase>LOWER</TrueCase>
            <TrueCaseText>yesterday</TrueCaseText>
          </token>
          <token id="10">
            <word>when</word>
            <lemma>when</lemma>
            <CharacterOffsetBegin>465</CharacterOffsetBegin>
            <CharacterOffsetEnd>469</CharacterOffsetEnd>
            <POS>WRB</POS>
            <TrueCase>LOWER</TrueCase>
            <TrueCaseText>when</TrueCaseText>
          </token>
          <token id="11">
            <word>a</word>
            <lemma>a</lemma>
            <CharacterOffsetBegin>470</CharacterOffsetBegin>
            <CharacterOffsetEnd>471</CharacterOffsetEnd>
            <POS>DT</POS>
            <TrueCase>LOWER</TrueCase>
            <TrueCaseText>a</TrueCaseText>
          </token>
          <token id="12">
            <word>judge</word>
            <lemma>judge</lemma>
            <CharacterOffsetBegin>472</CharacterOffsetBegin>
            <CharacterOffsetEnd>477</CharacterOffsetEnd>
            <POS>NN</POS>
            <TrueCase>LOWER</TrueCase>
            <TrueCaseText>judge</TrueCaseText>
          </token>
          <token id="13">
            <word>was</word>
            <lemma>be</lemma>
            <CharacterOffsetBegin>478</CharacterOffsetBegin>
            <CharacterOffsetEnd>481</CharacterOffsetEnd>
            <POS>VBD</POS>
            <TrueCase>LOWER</TrueCase>
            <TrueCaseText>was</TrueCaseText>
          </token>
          <token id="14">
            <word>considering</word>
            <lemma>consider</lemma>
            <CharacterOffsetBegin>482</CharacterOffsetBegin>
            <CharacterOffsetEnd>493</CharacterOffsetEnd>
            <POS>VBG</POS>
            <TrueCase>LOWER</TrueCase>
            <TrueCaseText>considering</TrueCaseText>
          </token>
          <token id="15">
            <word>whether</word>
            <lemma>whether</lemma>
            <CharacterOffsetBegin>494</CharacterOffsetBegin>
            <CharacterOffsetEnd>501</CharacterOffsetEnd>
            <POS>IN</POS>
            <TrueCase>LOWER</TrueCase>
            <TrueCaseText>whether</TrueCaseText>
          </token>
          <token id="16">
            <word>to</word>
            <lemma>to</lemma>
            <CharacterOffsetBegin>502</CharacterOffsetBegin>
            <CharacterOffsetEnd>504</CharacterOffsetEnd>
            <POS>TO</POS>
            <TrueCase>LOWER</TrueCase>
            <TrueCaseText>to</TrueCaseText>
          </token>
          <token id="17">
            <word>unseal</word>
            <lemma>unseal</lemma>
            <CharacterOffsetBegin>505</CharacterOffsetBegin>
            <CharacterOffsetEnd>511</CharacterOffsetEnd>
            <POS>JJ</POS>
            <TrueCase>LOWER</TrueCase>
            <TrueCaseText>unseal</TrueCaseText>
          </token>
          <token id="18">
            <word>warrants</word>
            <lemma>warrant</lemma>
            <CharacterOffsetBegin>512</CharacterOffsetBegin>
            <CharacterOffsetEnd>520</CharacterOffsetEnd>
            <POS>NNS</POS>
            <TrueCase>LOWER</TrueCase>
            <TrueCaseText>warrants</TrueCaseText>
          </token>
          <token id="19">
            <word>obtained</word>
            <lemma>obtain</lemma>
            <CharacterOffsetBegin>521</CharacterOffsetBegin>
            <CharacterOffsetEnd>529</CharacterOffsetEnd>
            <POS>VBN</POS>
            <TrueCase>LOWER</TrueCase>
            <TrueCaseText>obtained</TrueCaseText>
          </token>
          <token id="20">
            <word>before</word>
            <lemma>before</lemma>
            <CharacterOffsetBegin>530</CharacterOffsetBegin>
            <CharacterOffsetEnd>536</CharacterOffsetEnd>
            <POS>IN</POS>
            <TrueCase>LOWER</TrueCase>
            <TrueCaseText>before</TrueCaseText>
          </token>
          <token id="21">
            <word>scott</word>
            <lemma>scott</lemma>
            <CharacterOffsetBegin>537</CharacterOffsetBegin>
            <CharacterOffsetEnd>542</CharacterOffsetEnd>
            <POS>NN</POS>
            <TrueCase>INIT_UPPER</TrueCase>
            <TrueCaseText>Scott</TrueCaseText>
          </token>
          <token id="22">
            <word>peterson</word>
            <lemma>peterson</lemma>
            <CharacterOffsetBegin>543</CharacterOffsetBegin>
            <CharacterOffsetEnd>551</CharacterOffsetEnd>
            <POS>NN</POS>
            <TrueCase>INIT_UPPER</TrueCase>
            <TrueCaseText>Peterson</TrueCaseText>
          </token>
          <token id="23">
            <word>'s</word>
            <lemma>'s</lemma>
            <CharacterOffsetBegin>551</CharacterOffsetBegin>
            <CharacterOffsetEnd>553</CharacterOffsetEnd>
            <POS>POS</POS>
            <TrueCase>LOWER</TrueCase>
            <TrueCaseText>'s</TrueCaseText>
          </token>
          <token id="24">
            <word>arrest</word>
            <lemma>arrest</lemma>
            <CharacterOffsetBegin>554</CharacterOffsetBegin>
            <CharacterOffsetEnd>560</CharacterOffsetEnd>
            <POS>NN</POS>
            <TrueCase>LOWER</TrueCase>
            <TrueCaseText>arrest</TrueCaseText>
          </token>
          <token id="25">
            <word>.</word>
            <lemma>.</lemma>
            <CharacterOffsetBegin>560</CharacterOffsetBegin>
            <CharacterOffsetEnd>561</CharacterOffsetEnd>
            <POS>.</POS>
            <TrueCase>O</TrueCase>
            <TrueCaseText>.</TrueCaseText>
          </token>
        </tokens>
      </sentence>
      <sentence id="5">
        <tokens>
          <token id="1">
            <word>peterson</word>
            <lemma>peterson</lemma>
            <CharacterOffsetBegin>562</CharacterOffsetBegin>
            <CharacterOffsetEnd>570</CharacterOffsetEnd>
            <POS>NN</POS>
            <TrueCase>INIT_UPPER</TrueCase>
            <TrueCaseText>Peterson</TrueCaseText>
          </token>
          <token id="2">
            <word>awaiting</word>
            <lemma>await</lemma>
            <CharacterOffsetBegin>571</CharacterOffsetBegin>
            <CharacterOffsetEnd>579</CharacterOffsetEnd>
            <POS>VBG</POS>
            <TrueCase>LOWER</TrueCase>
            <TrueCaseText>awaiting</TrueCaseText>
          </token>
          <token id="3">
            <word>trial</word>
            <lemma>trial</lemma>
            <CharacterOffsetBegin>580</CharacterOffsetBegin>
            <CharacterOffsetEnd>585</CharacterOffsetEnd>
            <POS>NN</POS>
            <TrueCase>LOWER</TrueCase>
            <TrueCaseText>trial</TrueCaseText>
          </token>
          <token id="4">
            <word>in</word>
            <lemma>in</lemma>
            <CharacterOffsetBegin>586</CharacterOffsetBegin>
            <CharacterOffsetEnd>588</CharacterOffsetEnd>
            <POS>IN</POS>
            <TrueCase>LOWER</TrueCase>
            <TrueCaseText>in</TrueCaseText>
          </token>
          <token id="5">
            <word>the</word>
            <lemma>the</lemma>
            <CharacterOffsetBegin>589</CharacterOffsetBegin>
            <CharacterOffsetEnd>592</CharacterOffsetEnd>
            <POS>DT</POS>
            <TrueCase>LOWER</TrueCase>
            <TrueCaseText>the</TrueCaseText>
          </token>
          <token id="6">
            <word>murder</word>
            <lemma>murder</lemma>
            <CharacterOffsetBegin>593</CharacterOffsetBegin>
            <CharacterOffsetEnd>599</CharacterOffsetEnd>
            <POS>NN</POS>
            <TrueCase>LOWER</TrueCase>
            <TrueCaseText>murder</TrueCaseText>
          </token>
          <token id="7">
            <word>of</word>
            <lemma>of</lemma>
            <CharacterOffsetBegin>600</CharacterOffsetBegin>
            <CharacterOffsetEnd>602</CharacterOffsetEnd>
            <POS>IN</POS>
            <TrueCase>LOWER</TrueCase>
            <TrueCaseText>of</TrueCaseText>
          </token>
          <token id="8">
            <word>his</word>
            <lemma>he</lemma>
            <CharacterOffsetBegin>603</CharacterOffsetBegin>
            <CharacterOffsetEnd>606</CharacterOffsetEnd>
            <POS>PRP$</POS>
            <TrueCase>LOWER</TrueCase>
            <TrueCaseText>his</TrueCaseText>
          </token>
          <token id="9">
            <word>wife</word>
            <lemma>wife</lemma>
            <CharacterOffsetBegin>607</CharacterOffsetBegin>
            <CharacterOffsetEnd>611</CharacterOffsetEnd>
            <POS>NN</POS>
            <TrueCase>LOWER</TrueCase>
            <TrueCaseText>wife</TrueCaseText>
          </token>
          <token id="10">
            <word>lace</word>
            <lemma>lace</lemma>
            <CharacterOffsetBegin>612</CharacterOffsetBegin>
            <CharacterOffsetEnd>616</CharacterOffsetEnd>
            <POS>NN</POS>
            <TrueCase>LOWER</TrueCase>
            <TrueCaseText>lace</TrueCaseText>
          </token>
          <token id="11">
            <word>sand</word>
            <lemma>sand</lemma>
            <CharacterOffsetBegin>617</CharacterOffsetBegin>
            <CharacterOffsetEnd>621</CharacterOffsetEnd>
            <POS>NN</POS>
            <TrueCase>LOWER</TrueCase>
            <TrueCaseText>sand</TrueCaseText>
          </token>
          <token id="12">
            <word>their</word>
            <lemma>they</lemma>
            <CharacterOffsetBegin>622</CharacterOffsetBegin>
            <CharacterOffsetEnd>627</CharacterOffsetEnd>
            <POS>PRP$</POS>
            <TrueCase>LOWER</TrueCase>
            <TrueCaseText>their</TrueCaseText>
          </token>
          <token id="13">
            <word>unborn</word>
            <lemma>unborn</lemma>
            <CharacterOffsetBegin>628</CharacterOffsetBegin>
            <CharacterOffsetEnd>634</CharacterOffsetEnd>
            <POS>JJ</POS>
            <TrueCase>LOWER</TrueCase>
            <TrueCaseText>unborn</TrueCaseText>
          </token>
          <token id="14">
            <word>son</word>
            <lemma>son</lemma>
            <CharacterOffsetBegin>635</CharacterOffsetBegin>
            <CharacterOffsetEnd>638</CharacterOffsetEnd>
            <POS>NN</POS>
            <TrueCase>LOWER</TrueCase>
            <TrueCaseText>son</TrueCaseText>
          </token>
          <token id="15">
            <word>.</word>
            <lemma>.</lemma>
            <CharacterOffsetBegin>638</CharacterOffsetBegin>
            <CharacterOffsetEnd>639</CharacterOffsetEnd>
            <POS>.</POS>
            <TrueCase>O</TrueCase>
            <TrueCaseText>.</TrueCaseText>
          </token>
        </tokens>
      </sentence>
      <sentence id="6">
        <tokens>
          <token id="1">
            <word>joining</word>
            <lemma>join</lemma>
            <CharacterOffsetBegin>640</CharacterOffsetBegin>
            <CharacterOffsetEnd>647</CharacterOffsetEnd>
            <POS>VBG</POS>
            <TrueCase>INIT_UPPER</TrueCase>
            <TrueCaseText>Joining</TrueCaseText>
          </token>
          <token id="2">
            <word>us</word>
            <lemma>we</lemma>
            <CharacterOffsetBegin>648</CharacterOffsetBegin>
            <CharacterOffsetEnd>650</CharacterOffsetEnd>
            <POS>PRP</POS>
            <TrueCase>LOWER</TrueCase>
            <TrueCaseText>us</TrueCaseText>
          </token>
          <token id="3">
            <word>,</word>
            <lemma>,</lemma>
            <CharacterOffsetBegin>650</CharacterOffsetBegin>
            <CharacterOffsetEnd>651</CharacterOffsetEnd>
            <POS>,</POS>
            <TrueCase>O</TrueCase>
            <TrueCaseText>,</TrueCaseText>
          </token>
          <token id="4">
            <word>beth</word>
            <lemma>beth</lemma>
            <CharacterOffsetBegin>652</CharacterOffsetBegin>
            <CharacterOffsetEnd>656</CharacterOffsetEnd>
            <POS>NN</POS>
            <TrueCase>INIT_UPPER</TrueCase>
            <TrueCaseText>Beth</TrueCaseText>
          </token>
          <token id="5">
            <word>caras</word>
            <lemma>cara</lemma>
            <CharacterOffsetBegin>657</CharacterOffsetBegin>
            <CharacterOffsetEnd>662</CharacterOffsetEnd>
            <POS>NNS</POS>
            <TrueCase>INIT_UPPER</TrueCase>
            <TrueCaseText>Caras</TrueCaseText>
          </token>
          <token id="6">
            <word>.</word>
            <lemma>.</lemma>
            <CharacterOffsetBegin>662</CharacterOffsetBegin>
            <CharacterOffsetEnd>663</CharacterOffsetEnd>
            <POS>.</POS>
            <TrueCase>O</TrueCase>
            <TrueCaseText>.</TrueCaseText>
          </token>
        </tokens>
      </sentence>
      <sentence id="7">
        <tokens>
          <token id="1">
            <word>good</word>
            <lemma>good</lemma>
            <CharacterOffsetBegin>664</CharacterOffsetBegin>
            <CharacterOffsetEnd>668</CharacterOffsetEnd>
            <POS>JJ</POS>
            <TrueCase>INIT_UPPER</TrueCase>
            <TrueCaseText>Good</TrueCaseText>
          </token>
          <token id="2">
            <word>morning</word>
            <lemma>morning</lemma>
            <CharacterOffsetBegin>669</CharacterOffsetBegin>
            <CharacterOffsetEnd>676</CharacterOffsetEnd>
            <POS>NN</POS>
            <TrueCase>LOWER</TrueCase>
            <TrueCaseText>morning</TrueCaseText>
          </token>
          <token id="3">
            <word>once</word>
            <lemma>once</lemma>
            <CharacterOffsetBegin>677</CharacterOffsetBegin>
            <CharacterOffsetEnd>681</CharacterOffsetEnd>
            <POS>RB</POS>
            <TrueCase>LOWER</TrueCase>
            <TrueCaseText>once</TrueCaseText>
          </token>
          <token id="4">
            <word>again</word>
            <lemma>again</lemma>
            <CharacterOffsetBegin>682</CharacterOffsetBegin>
            <CharacterOffsetEnd>687</CharacterOffsetEnd>
            <POS>RB</POS>
            <TrueCase>LOWER</TrueCase>
            <TrueCaseText>again</TrueCaseText>
          </token>
          <token id="5">
            <word>.</word>
            <lemma>.</lemma>
            <CharacterOffsetBegin>687</CharacterOffsetBegin>
            <CharacterOffsetEnd>688</CharacterOffsetEnd>
            <POS>.</POS>
            <TrueCase>O</TrueCase>
            <TrueCaseText>.</TrueCaseText>
          </token>
        </tokens>
      </sentence>
      <sentence id="8">
        <tokens>
          <token id="1">
            <word>thanks</word>
            <lemma>thanks</lemma>
            <CharacterOffsetBegin>689</CharacterOffsetBegin>
            <CharacterOffsetEnd>695</CharacterOffsetEnd>
            <POS>NNS</POS>
            <TrueCase>INIT_UPPER</TrueCase>
            <TrueCaseText>Thanks</TrueCaseText>
          </token>
          <token id="2">
            <word>for</word>
            <lemma>for</lemma>
            <CharacterOffsetBegin>696</CharacterOffsetBegin>
            <CharacterOffsetEnd>699</CharacterOffsetEnd>
            <POS>IN</POS>
            <TrueCase>LOWER</TrueCase>
            <TrueCaseText>for</TrueCaseText>
          </token>
          <token id="3">
            <word>being</word>
            <lemma>be</lemma>
            <CharacterOffsetBegin>700</CharacterOffsetBegin>
            <CharacterOffsetEnd>705</CharacterOffsetEnd>
            <POS>VBG</POS>
            <TrueCase>LOWER</TrueCase>
            <TrueCaseText>being</TrueCaseText>
          </token>
          <token id="4">
            <word>with</word>
            <lemma>with</lemma>
            <CharacterOffsetBegin>706</CharacterOffsetBegin>
            <CharacterOffsetEnd>710</CharacterOffsetEnd>
            <POS>IN</POS>
            <TrueCase>LOWER</TrueCase>
            <TrueCaseText>with</TrueCaseText>
          </token>
          <token id="5">
            <word>us</word>
            <lemma>we</lemma>
            <CharacterOffsetBegin>711</CharacterOffsetBegin>
            <CharacterOffsetEnd>713</CharacterOffsetEnd>
            <POS>PRP</POS>
            <TrueCase>LOWER</TrueCase>
            <TrueCaseText>us</TrueCaseText>
          </token>
          <token id="6">
            <word>.</word>
            <lemma>.</lemma>
            <CharacterOffsetBegin>713</CharacterOffsetBegin>
            <CharacterOffsetEnd>714</CharacterOffsetEnd>
            <POS>.</POS>
            <TrueCase>O</TrueCase>
            <TrueCaseText>.</TrueCaseText>
          </token>
        </tokens>
      </sentence>
      <sentence id="9">
        <tokens>
          <token id="1">
            <word>&lt;/TURN&gt;</word>
            <lemma>&lt;/turn&gt;</lemma>
            <CharacterOffsetBegin>715</CharacterOffsetBegin>
            <CharacterOffsetEnd>722</CharacterOffsetEnd>
            <POS>NN</POS>
            <TrueCase>O</TrueCase>
            <TrueCaseText>&lt;/TURN&gt;</TrueCaseText>
          </token>
          <token id="2">
            <word>&lt;/TEXT&gt;</word>
            <lemma>&lt;/text&gt;</lemma>
            <CharacterOffsetBegin>723</CharacterOffsetBegin>
            <CharacterOffsetEnd>730</CharacterOffsetEnd>
            <POS>NN</POS>
            <TrueCase>O</TrueCase>
            <TrueCaseText>&lt;/TEXT&gt;</TrueCaseText>
          </token>
          <token id="3">
            <word>&lt;/BODY&gt;</word>
            <lemma>&lt;/body&gt;</lemma>
            <CharacterOffsetBegin>731</CharacterOffsetBegin>
            <CharacterOffsetEnd>738</CharacterOffsetEnd>
            <POS>NN</POS>
            <TrueCase>O</TrueCase>
            <TrueCaseText>&lt;/BODY&gt;</TrueCaseText>
          </token>
          <token id="4">
            <word>&lt;ENDTIME&gt;</word>
            <lemma>&lt;endtime&gt;</lemma>
            <CharacterOffsetBegin>739</CharacterOffsetBegin>
            <CharacterOffsetEnd>748</CharacterOffsetEnd>
            <POS>NN</POS>
            <TrueCase>O</TrueCase>
            <TrueCaseText>&lt;ENDTIME&gt;</TrueCaseText>
          </token>
          <token id="5">
            <word>2003-06-04</word>
            <lemma>2003-06-04</lemma>
            <CharacterOffsetBegin>749</CharacterOffsetBegin>
            <CharacterOffsetEnd>759</CharacterOffsetEnd>
            <POS>CD</POS>
            <TrueCase>O</TrueCase>
            <TrueCaseText>2003-06-04</TrueCaseText>
          </token>
          <token id="6">
            <word>09:42:40</word>
            <lemma>09:42:40</lemma>
            <CharacterOffsetBegin>760</CharacterOffsetBegin>
            <CharacterOffsetEnd>768</CharacterOffsetEnd>
            <POS>CD</POS>
            <TrueCase>O</TrueCase>
            <TrueCaseText>09:42:40</TrueCaseText>
          </token>
          <token id="7">
            <word>&lt;/ENDTIME&gt;</word>
            <lemma>&lt;/endtime&gt;</lemma>
            <CharacterOffsetBegin>769</CharacterOffsetBegin>
            <CharacterOffsetEnd>779</CharacterOffsetEnd>
            <POS>NN</POS>
            <TrueCase>O</TrueCase>
            <TrueCaseText>&lt;/ENDTIME&gt;</TrueCaseText>
          </token>
          <token id="8">
            <word>&lt;/DOC&gt;</word>
            <lemma>&lt;/doc&gt;</lemma>
            <CharacterOffsetBegin>780</CharacterOffsetBegin>
            <CharacterOffsetEnd>786</CharacterOffsetEnd>
            <POS>NN</POS>
            <TrueCase>O</TrueCase>
            <TrueCaseText>&lt;/DOC&gt;</TrueCaseText>
          </token>
        </tokens>
      </sentence>
    </sentences>
  </document>
</root>
